mdhelper/__init__.py
mdhelper/algorithm/__init__.py
mdhelper/algorithm/accelerated.py
mdhelper/algorithm/correlation.py
mdhelper/algorithm/molecule.py
mdhelper/algorithm/topology.py
mdhelper/algorithm/unit.py
mdhelper/algorithm/utility.py
mdhelper/analysis/__init__.py
mdhelper/analysis/base.py
mdhelper/analysis/electrostatics.py
mdhelper/analysis/polymer.py
mdhelper/analysis/profile.py
mdhelper/analysis/structure.py
mdhelper/analysis/thermodynamics.py
mdhelper/analysis/transport.py
mdhelper/fit/__init__.py
mdhelper/fit/distribution.py
mdhelper/fit/exponential.py
mdhelper/fit/fourier.py
mdhelper/fit/gaussian.py
mdhelper/fit/polynomial.py
mdhelper/fit/power.py
mdhelper/lammps/__init__.py
mdhelper/lammps/topology.py
mdhelper/openmm/__init__.py
mdhelper/openmm/bond.py
mdhelper/openmm/file.py
mdhelper/openmm/pair.py
mdhelper/openmm/reporter.py
mdhelper/openmm/system.py
mdhelper/openmm/topology.py
mdhelper/openmm/unit.py
mdhelper/openmm/utility.py
mdhelper/plot/__init__.py
mdhelper/plot/axis.py
mdhelper/plot/color.py
mdhelper/plot/rcparam.py
mdhelper-1.0.0.dist-info/LICENSE
mdhelper-1.0.0.dist-info/METADATA
mdhelper-1.0.0.dist-info/WHEEL
mdhelper-1.0.0.dist-info/top_level.txt
mdhelper-1.0.0.dist-info/RECORD
