Metadata-Version: 2.1
Name: mdhelper
Version: 1.0.0
Summary: A batteries-included toolkit of analysis modules and helper functions 
Author-email: "Benjamin B. Ye" <bye@caltech.edu>, "Pierre J. Walker" <pjwalker@caltech.edu>
License: GNU GENERAL PUBLIC LICENSE
Project-URL: Homepage, https://github.com/bbye98/mdhelper
Project-URL: Bug Tracker, https://github.com/bbye98/mdhelper/issues
Classifier: Intended Audience :: Science/Research
Classifier: License :: OSI Approved :: GNU General Public License v3 or later (GPLv3+)
Classifier: Operating System :: OS Independent
Classifier: Programming Language :: Python
Classifier: Programming Language :: Python :: 3
Requires-Python: >=3.9
License-File: LICENSE
Requires-Dist: matplotlib
Requires-Dist: mdanalysis
Requires-Dist: netCDF4
Requires-Dist: numpy
Requires-Dist: pandas
Requires-Dist: pint
Requires-Dist: scipy
Requires-Dist: sympy
